copx/__init__.py
copx/copx_fastapi.py
copx/copx_mcp.py
copx/flow.py
copx/nodes.py
copx/project_declaration_map.py
copx/project_tree.py
copx/semantic_search.py
copx/test.py
copx/utils.py
copx/prompts/__init__.py
copx/prompts/answer.py
copx/prompts/prompt.py
copx/symbal_extractor/__init__.py
copx/symbal_extractor/symbol_extractor.py
copx/tools/__init__.py
copx/tools/tool_grep_declaration_map.py
copx/tools/tool_grep_search.py
copx/tools/tool_view_file_content.py
copx/tools/tool_view_file_declaration_map.py
copx/tools/use_tools.py
copx-0.1.4.dist-info/licenses/LICENSE
copx-0.1.4.dist-info/METADATA
copx-0.1.4.dist-info/WHEEL
copx-0.1.4.dist-info/entry_points.txt
copx-0.1.4.dist-info/top_level.txt
copx-0.1.4.dist-info/RECORD
