Metadata-Version: 2.4
Name: copx
Version: 0.1.4
Summary: copx-mcp
Requires-Python: >=3.13
License-File: LICENSE
Requires-Dist: aiofiles>=24.1.0
Requires-Dist: fastapi[standard]>=0.115.12
Requires-Dist: litellm>=1.70.4
Requires-Dist: mcp[cli]>=1.9.1
Requires-Dist: pathspec>=0.12.1
Requires-Dist: pocketflow>=0.0.2
Requires-Dist: tree-sitter>=0.24.0
Requires-Dist: tree-sitter-go>=0.23.4
Requires-Dist: tree-sitter-javascript>=0.23.1
Requires-Dist: tree-sitter-python>=0.23.6
Requires-Dist: tree-sitter-c>=0.20.0
Requires-Dist: tree-sitter-cpp>=0.20.1
Requires-Dist: tree-sitter-typescript>=0.23.2
Dynamic: license-file
